README.md
setup.cfg
setup.py
hasl/__init__.py
hasl/exceptions.py
hasl/hasl.py
hasl/version.py
hasl.egg-info/PKG-INFO
hasl.egg-info/SOURCES.txt
hasl.egg-info/dependency_links.txt
hasl.egg-info/requires.txt
hasl.egg-info/top_level.txt