Metadata-Version: 2.1
Name: hasl
Version: 1.1.0
Summary: Communications Module for HomeAssistant SL Sensor
Home-page: https://github.com/dsorlov/hasl
Author: Daniel Sorlov
Author-email: daniel@sorlov.com
License: UNKNOWN
Platform: UNKNOWN
Classifier: Programming Language :: Python :: 3
Classifier: License :: OSI Approved :: Apache Software License
Classifier: Operating System :: OS Independent
